<?xml version="1.0" ?>
<ROOT>
	
	
	
	
	<BillInformation>
		
		
		
		
		<BillNumber>HB916</BillNumber>
		
		
		
		
		<CurrentBillString>HB 916</CurrentBillString>
		
		
		
		
		<SubstitutedBy/>
		
		
		
		
		<Title>
			
			
			
			
			<ShortTitle>MISSOURI CHILD AND ADOLESCENT PROTECTION ACT</ShortTitle>
			
			
			
			
			<LongTitle>Creates provisions relating to gender transition procedures</LongTitle>
			
			
		
		
		</Title>
		
		
		
		
		<Action>
			
			
			
			
			<Link>https://house.mo.gov/bill.aspx?bill=HB916&amp;year=2023&amp;code=R </Link>
			
			
			
			
			<Description>Introduced and Read First Time (H)</Description>
			
			
			
			
			<Guid>535850</Guid>
			
			
			
			
			<PubDate>2023-01-23</PubDate>
			
			
			
			
			<HouseJournalStartPage>381</HouseJournalStartPage>
			
			
			
			
			<HouseJournalEndPage>381</HouseJournalEndPage>
			
			
			
			
			<JournalLink>https://documents.house.mo.gov/BillTracking/bills231/jrnpdf/jrn010.pdf#page=381</JournalLink>
			
			
		
		
		</Action>
		
		
		
		
		<Action>
			
			
			
			
			<Link>https://house.mo.gov/bill.aspx?bill=HB916&amp;year=2023&amp;code=R </Link>
			
			
			
			
			<Description>Read Second Time (H)</Description>
			
			
			
			
			<Guid>535940</Guid>
			
			
			
			
			<PubDate>2023-01-24</PubDate>
			
			
			
			
			<HouseJournalStartPage>396</HouseJournalStartPage>
			
			
			
			
			<HouseJournalEndPage>396</HouseJournalEndPage>
			
			
			
			
			<JournalLink>https://documents.house.mo.gov/BillTracking/bills231/jrnpdf/jrn011.pdf#page=396</JournalLink>
			
			
		
		
		</Action>
		
		
		
		
		<Action>
			
			
			
			
			<Link>https://house.mo.gov/bill.aspx?bill=HB916&amp;year=2023&amp;code=R </Link>
			
			
			
			
			<Description>Referred: General Laws(H)</Description>
			
			
			
			
			<Guid>536100</Guid>
			
			
			
			
			<PubDate>2023-01-25</PubDate>
			
			
			
			
			<HouseJournalStartPage>410</HouseJournalStartPage>
			
			
			
			
			<HouseJournalEndPage>410</HouseJournalEndPage>
			
			
			
			
			<JournalLink>https://documents.house.mo.gov/BillTracking/bills231/jrnpdf/jrn012.pdf#page=410</JournalLink>
			
			
		
		
		</Action>
		
		
		
		
		<Sponsor>
			
			
			
			
			<SponsorType>Co-Sponsor</SponsorType>
			
			
			
			
			<FullName>Hannah Kelly</FullName>
			
			
			
			
			<District>141</District>
			
			
		
		
		</Sponsor>
		
		
		
		
		<Sponsor>
			
			
			
			
			<SponsorType>Co-Sponsor</SponsorType>
			
			
			
			
			<FullName>Hardy Billington</FullName>
			
			
			
			
			<District>152</District>
			
			
		
		
		</Sponsor>
		
		
		
		
		<Sponsor>
			
			
			
			
			<SponsorType>Co-Sponsor</SponsorType>
			
			
			
			
			<FullName>Mike McGirl</FullName>
			
			
			
			
			<District>118</District>
			
			
		
		
		</Sponsor>
		
		
		
		
		<Sponsor>
			
			
			
			
			<SponsorType>Co-Sponsor</SponsorType>
			
			
			
			
			<FullName>Justin Sparks</FullName>
			
			
			
			
			<District>110</District>
			
			
		
		
		</Sponsor>
		
		
		
		
		<Sponsor>
			
			
			
			
			<SponsorType>Sponsor</SponsorType>
			
			
			
			
			<FullName>Cyndi Buchheit-Courtway</FullName>
			
			
			
			
			<District>115</District>
			
			
		
		
		</Sponsor>
		
		
		
		
		<BillText>
			
			
			
			
			<BillTextLink>https://documents.house.mo.gov/billtracking/bills231/hlrbillspdf/1850H.02I.pdf</BillTextLink>
			
			
			
			
			<DocumentName>Introduced</DocumentName>
			
			
			
			
			<VersionTypeCode>IN</VersionTypeCode>
			
			
		
		
		</BillText>
		
		
		
		
		<BillSummary>
			
			
			
			
			<SummaryTextLink>https://documents.house.mo.gov/billtracking/bills231/sumpdf/HB0916I.pdf</SummaryTextLink>
			
			
			
			
			<DocumentName>Introduced</DocumentName>
			
			
			
			
			<VersionTypeCode>IN</VersionTypeCode>
			
			
		
		
		</BillSummary>
		
		
		
		
		<FiscalNote>
			
			
			
			
			<FiscalNoteLink>https://documents.house.mo.gov/billtracking/bills231/fiscal/fispdf/1850H.02I.ORG.pdf</FiscalNoteLink>
			
			
		
		
		</FiscalNote>
		
		
	
	
	</BillInformation>
	
	


</ROOT>
